[
    {
        "Лема": "ἅρπαξ, ἅρπαγος, ὁ",
        "Превод": "граблив"
    },
    {
        "Лема": "μερόψ, -οπος",
        "Превод": "смъртен"
    },
    {
        "Лема": "φυγάς, άδος, ὁ",
        "Превод": "изгонен, беглец"
    },
    {
        "Лема": "πὲνης, -ητος, ὁ",
        "Превод": "беден"
    },
    {
        "Лема": "ἀγνώς, ῶτος, ὁ",
        "Превод": "непознат"
    },
    {
        "Лема": "ἄπαις, ἄπαιδος, ὁ",
        "Превод": "бездетен"
    },
    {
        "Лема": "μάκαρ, μάκαρος",
        "Превод": "блажен"
    },
    {
        "Лема": "αὐχήν, ενος, ἡ",
        "Превод": "врат, шия"
    },
    {
        "Лема": "εὐδαίμων, εὐδαίμονος",
        "Превод": "щастлив"
    },
    {
        "Лема": "ἄχαρις, ἀχάριτος",
        "Превод": "неблагодарен, неприятен"
    },
    {
        "Лема": "ἀπάτωρ, ἄπατορος",
        "Превод": "без баща"
    },
    {
        "Лема": "εὐδαίμων, εὐδαίμονος",
        "Превод": "щастлив"
    },
    {
        "Лема": "ἄρρην, ἄρρενος",
        "Превод": "мъжки"
    },
    {
        "Лема": "σώφρων, σῶφρονος",
        "Превод": "разумен"
    },
    {
        "Лема": "ἐπιστήμων, ἐπιστήμονος",
        "Превод": "знаещ, умел"
    }
]
